github_contributions/__init__.py
github_contributions/contributions.py
github_contributions/exceptions.py
github_contributions/user.py
github_contributions/utils.py
GithubContributions-0.3.0.dist-info/LICENSE
GithubContributions-0.3.0.dist-info/METADATA
GithubContributions-0.3.0.dist-info/WHEEL
GithubContributions-0.3.0.dist-info/top_level.txt
GithubContributions-0.3.0.dist-info/RECORD
